Metadata-Version: 1.2
Name: bimeta
Version: 1.3.4
Summary: bimeta client
Home-page: https://github.com/trbpnd/bimeta
Author: tr-
Author-email: rahmanovic@gmail.com
License: MIT
Platform: UNKNOWN
Requires-Python: >3.5.2
